nautobot_utsc/__init__.py
nautobot_utsc/diffsync/__init__.py
nautobot_utsc/diffsync/bluecat/__init__.py
nautobot_utsc/diffsync/bluecat/adapters.py
nautobot_utsc/diffsync/bluecat/models.py
nautobot_utsc/diffsync/yaml/__init__.py
nautobot_utsc/diffsync/yaml/adapters.py
nautobot_utsc/diffsync/yaml/models.py
nautobot_utsc/diffsync/yaml/test.yaml
nautobot_utsc/jobs.py
nautobot_utsc/nautobot_config.py
nautobot_utsc-2022.5.10.2.dist-info/WHEEL
nautobot_utsc-2022.5.10.2.dist-info/METADATA
nautobot_utsc-2022.5.10.2.dist-info/RECORD
